EXAMPLE_BUNDLE/__init__.py
EXAMPLE_BUNDLE/experiment.py
OM2_EXAMPLE/__init__.py
OM2_EXAMPLE/experiment.py
example_bundle_nbx/__init__.py
example_bundle_nbx/experiment.py
example_bundle_nbx/wrapper.py
nbx/__init__.py
nbx/_nbdev.py
nbx/om.py
nbx/om2.py
nbx/pspace.py
nbx/templ.py
nbx/templates/__init__.py
nbx/templates/experiment.tpl
nbx/templates/experiment_jl.tpl
nbx/templates/experiment_py.tpl
nbx/templates/job.tpl
nbx/templates/job_jl.tpl
nbx/templates/job_py.tpl
nbx/templates/pspace jl.tpl
nbx/templates/pspace_jl.tpl
nbx/templates/run.tpl
nbx/templates/wrapper.tpl
nbx/templates/wrapper_jl.tpl
nbx/templates/wrapper_py.tpl
test_nbx/__init__.py
test_nbx/experiment.py
test_nbx/wrapper.py
nbx-0.3.0.dist-info/LICENSE
nbx-0.3.0.dist-info/METADATA
nbx-0.3.0.dist-info/WHEEL
nbx-0.3.0.dist-info/entry_points.txt
nbx-0.3.0.dist-info/top_level.txt
nbx-0.3.0.dist-info/RECORD
