Metadata-Version: 2.1
Name: nbx
Version: 0.3.0
Summary: This module enables you to quickly convert your jupyter notebook into a bundle of files that can be run on BCS'*OpenMind*
Home-page: https://github.com/mirkoklukas/nbx
Author: Mirko Klukas
Author-email: mirko.klukas@gmail.com
License: Apache Software License 2.0
Keywords: openmind; mit
Platform: UNKNOWN
Classifier: Development Status :: 3 - Alpha
Classifier: Intended Audience :: Science/Research
Classifier: License :: OSI Approved :: Apache Software License
Classifier: Natural Language :: English
Classifier: Programming Language :: Python :: 3.5
Classifier: Programming Language :: Python :: 3.6
Classifier: Programming Language :: Python :: 3.7
Classifier: Programming Language :: Python :: 3.8
Requires-Python: >=3.5
